{
    "typename": "GraphImage",
    "date": "2017-10-24T08:03:04",
    "caption": "\u201c\u2026tomorrow's energy future may be more sustainable than today\u2026\u201d #GenEnergy",
    "url": "https://instagram.fyvr3-1.fna.fbcdn.net/vp/a81cff0e68fc58dc545d0cfd0f2fc02f/5AEFD35B/t51.2885-15/e35/22709545_122710568400630_7825483061021114368_n.jpg",
    "mediaid": 1632736538348261544,
    "is_video": false,
    "owner_username": "naturalresourcescanada",
    "shortcode": "BaopTskDJCo",
    "tagged_users": [],
    "comments": 0,
    "caption_hashtags": [
        "genenergy"
    ],
    "owner_id": 4211313612,
    "likes": 8,
    "caption_mentions": []
}