{
    "owner_id": 4143631778,
    "date": "2017-11-12T17:31:46",
    "url": "https://instagram.fyvr3-1.fna.fbcdn.net/vp/a38e3fe54c4884b6dd0cc9dbb831dc17/5AE0DAA9/t51.2885-15/e35/23498161_1672130259474009_7255109097714876416_n.jpg",
    "typename": "GraphImage",
    "owner_username": "parks.canada",
    "caption_hashtags": [
        "parkscanada",
        "canada150",
        "travel",
        "travelgram",
        "explorecanada",
        "wanderlust",
        "discovercanada",
        "landscape",
        "sunrise",
        "instatravel",
        "tourist",
        "vacation",
        "instagood",
        "wander",
        "travelbug",
        "instaexplore",
        "canada",
        "canadian",
        "brucepeninsula",
        "brucepeninsulanp",
        "tobermory",
        "ontario",
        "travelontario",
        "discoverontario"
    ],
    "shortcode": "BbasXHnHcql",
    "caption_mentions": [
        "colethorsen"
    ],
    "mediaid": 1646823716524247717,
    "comments": 41,
    "is_video": false,
    "likes": 4661,
    "tagged_users": [],
    "caption": "When the sunrise view is more impressive than any watercolour painting you\u2019ve ever seen\u2026\n.\n.\n.\n\ud83d\udccd: Bruce Peninsula National Park .\n\ud83d\udcf7: @colethorsen .\n.\n.\n#ParksCanada #Canada150 #Travel Travelphotography #Travelgram #ExploreCanada #Wanderlust #DiscoverCanada #Landscape #Sunrise #Instatravel #tourist #Vacation #instagood #wander #travelbug #instaexplore #canada #canadian #brucepeninsula #brucepeninsulaNP #tobermory #Ontario #TravelOntario #DiscoverOntario"
}