{
    "likes": 223,
    "mediaid": 1633702835836538180,
    "owner_id": 4141034395,
    "is_video": false,
    "date": "2017-10-25T16:02:56",
    "caption_mentions": [
        "amandaglasel"
    ],
    "owner_username": "parcs.canada",
    "url": "https://instagram.fyvr3-1.fna.fbcdn.net/vp/b9df2f7aecf69dd825177f9725fea665/5AE45065/t51.2885-15/e35/22793826_290631761341066_1364485310070652928_n.jpg",
    "tagged_users": [],
    "comments": 0,
    "caption": "Il y a quelque chose d\u2019unique \u00e0 propos du ciel de la prairie... \ud83d\ude0d Est-ce une photo ou une aquarelle?\n\ud83d\udccd Parc national de Prince Albert\n\ud83d\udcf7 : @amandaglasel\n.\n.\n.\n.\n.\n#nature #photographie #sauvage #voyage #jouerdehors #aventure #paysage #parcscanada #canada150 #canada #explorecanada #conservation #PNPrinceAlbert #ExploreSask",
    "shortcode": "BasFBLOlc1E",
    "typename": "GraphImage",
    "caption_hashtags": [
        "nature",
        "photographie",
        "sauvage",
        "voyage",
        "jouerdehors",
        "aventure",
        "paysage",
        "parcscanada",
        "canada150",
        "canada",
        "explorecanada",
        "conservation",
        "pnprincealbert",
        "exploresask"
    ]
}