{
    "likes": 140,
    "mediaid": 1475619838202601914,
    "owner_id": 4141034395,
    "is_video": false,
    "date": "2017-03-21T13:20:14",
    "caption_mentions": [
        "taylormichaelburk"
    ],
    "owner_username": "parcs.canada",
    "url": "https://instagram.fyvr3-1.fna.fbcdn.net/vp/2c7d784529326f6e0e9fa17d5ac06361/5AE498E9/t51.2885-15/e35/19379561_1240623009379433_4607147573730344960_n.jpg",
    "tagged_users": [],
    "comments": 1,
    "caption": "Bonne Journ\u00e9e internationale des #for\u00eats, probablement l'une de nos journ\u00e9es pr\u00e9f\u00e9r\u00e9es de l'ann\u00e9e! \ud83c\udf32 \ud83c\udf32 \ud83c\udf32 \nSaviez-vous que l'un de nos parcs abrite une for\u00eat pluviale? Ce n\u2019est pas une blague! Dans la r\u00e9serve de parc national Pacific Rim, vous trouverez des arbres tordus et rabougris dont les formes diff\u00e8rent les unes des autres, ainsi qu'une v\u00e9g\u00e9tation tellement dense qu'il est impossible de voir le sol. Cette abondance de plantes s\u2019explique par une grande quantit\u00e9 de pluie dans le parc et par sa proximit\u00e9 avec l'oc\u00e9an Pacifique. \ud83c\udf27\ufe0f Photo de @taylormichaelburk \n#parcscanada #canada #canada150 #explorecanada #explorecb #forets #foret #foretpluviale #pacificrim #RPNpacificrim #hellobc #colombiebritannique #conservation #pluie #ocean #oceanpacifique #eau",
    "shortcode": "BR6dGy3leG6",
    "typename": "GraphImage",
    "caption_hashtags": [
        "for\u00eats",
        "parcscanada",
        "canada",
        "canada150",
        "explorecanada",
        "explorecb",
        "forets",
        "foret",
        "foretpluviale",
        "pacificrim",
        "rpnpacificrim",
        "hellobc",
        "colombiebritannique",
        "conservation",
        "pluie",
        "ocean",
        "oceanpacifique",
        "eau"
    ]
}