{
    "typename": "GraphImage",
    "caption": "Occasions et d\u00e9fis li\u00e9s \u00e0 l\u2019avenir \u00e9nerg\u00e9tique du Canada: id\u00e9es g\u00e9niales \u00e9chang\u00e9es auj \u00e0 l\u2019atelier #G\u00e9n\u00c9nergie \u00e0 Halifax avec Maritimes Energy",
    "date": "2017-08-29T13:25:09",
    "caption_hashtags": [
        "g\u00e9n\u00e9nergie"
    ],
    "comments": 0,
    "url": "https://instagram.fyvr3-1.fna.fbcdn.net/vp/90017ec29f9f864355ab9f3e4efaef45/5AEB0AD1/t51.2885-15/e35/21224590_299655663842579_6634307893321531392_n.jpg",
    "owner_username": "ressourcesnaturellescanada",
    "mediaid": 1592311211068675597,
    "caption_mentions": [],
    "likes": 2,
    "is_video": false,
    "owner_id": 4210755410,
    "tagged_users": [],
    "shortcode": "BYZBpwrntYN"
}