{
    "likes": 27,
    "mediaid": 1395803839567223379,
    "owner_id": 4141034395,
    "is_video": false,
    "date": "2016-12-01T09:20:05",
    "caption_mentions": [],
    "owner_username": "parcs.canada",
    "url": "https://instagram.fyvr3-1.fna.fbcdn.net/vp/f170ee930a4862e971c6f406b5a0f5af/5AEBBC56/t51.2885-15/e35/19379530_241139069709111_6512404712732491776_n.jpg",
    "tagged_users": [],
    "comments": 4,
    "caption": "Un cadeau du Canada pour vous : la carte d\u2019entr\u00e9e D\u00e9couverte 2017 vous donne acc\u00e8s gratuitement aux endroits de #ParcsCanada! EN PRIME : Commandez votre laissez-passer #gratuit et vous serez inscrit \u00e0 notre #CONCOURS pour courir la chance de gagner un voyage inoubliable au magnifique parc national du #GrosMorne. Cliquez sur le lien dans notre bio pour obtenir plus d\u2019information.\n\n#Canada150 #Entr\u00e9eGratuiteEn2017 #VoyageduneVie #ExploreCanada #PNGrosMorne #TerreNeuve",
    "shortcode": "BNe5DJhh9pT",
    "typename": "GraphImage",
    "caption_hashtags": [
        "parcscanada",
        "gratuit",
        "concours",
        "grosmorne",
        "canada150",
        "entr\u00e9egratuiteen2017",
        "voyagedunevie",
        "explorecanada",
        "pngrosmorne",
        "terreneuve"
    ]
}