[
    {
        "text": "@ricardoantoniocm \ud83d\ude0d",
        "created_at": 1487118643,
        "owner": {
            "username": "daimalee21",
            "profile_pic_url": "https://instagram.fyvr3-1.fna.fbcdn.net/t51.2885-19/s150x150/24327987_388383674955488_7047847505156898816_n.jpg",
            "id": "302539190"
        },
        "id": "17861279722118087"
    },
    {
        "text": "@elsy_HM",
        "created_at": 1487114338,
        "owner": {
            "username": "cmrmap",
            "profile_pic_url": "https://instagram.fyvr3-1.fna.fbcdn.net/t51.2885-19/s150x150/25006100_1992032934146686_5787487131647606784_n.jpg",
            "id": "938764511"
        },
        "id": "17861382637109469"
    },
    {
        "text": "So sweet!",
        "created_at": 1487110599,
        "owner": {
            "username": "lianapv508",
            "profile_pic_url": "https://instagram.fyvr3-1.fna.fbcdn.net/t51.2885-19/s150x150/23279835_149339945683329_322967646439997440_n.jpg",
            "id": "1511095857"
        },
        "id": "17866104850066523"
    }
]