[
    {
        "text": "\ud83d\udc4d\ud83d\udc4d",
        "created_at": 1498746481,
        "owner": {
            "username": "evermaven",
            "profile_pic_url": "https://instagram.fyvr3-1.fna.fbcdn.net/t51.2885-19/11428610_480890778733484_418970124_a.jpg",
            "id": "1726906574"
        },
        "id": "17871767554092011"
    },
    {
        "text": "@tyx226 damn I wonder which trail this one is. Next time",
        "created_at": 1497588723,
        "owner": {
            "username": "robertzhu",
            "profile_pic_url": "https://instagram.fyvr3-1.fna.fbcdn.net/t51.2885-19/11327835_944662168890231_390393136_a.jpg",
            "id": "30765522"
        },
        "id": "17884220113009284"
    },
    {
        "text": "@dyl4nkelly",
        "created_at": 1494284750,
        "owner": {
            "username": "cass_helder",
            "profile_pic_url": "https://instagram.fyvr3-1.fna.fbcdn.net/t51.2885-19/s150x150/18514144_355427741522168_1840096235944411136_a.jpg",
            "id": "227085138"
        },
        "id": "17855454046179907"
    },
    {
        "text": "@m.gills9_",
        "created_at": 1493784455,
        "owner": {
            "username": "juliamamone",
            "profile_pic_url": "https://instagram.fyvr3-1.fna.fbcdn.net/t51.2885-19/s150x150/13562097_103036646796930_1658478107_a.jpg",
            "id": "486522924"
        },
        "id": "17881641019060032"
    },
    {
        "text": "@sylviakennedy613 Excited to see you then! \ud83d\ude0a\ud83c\udfd4",
        "created_at": 1493751861,
        "owner": {
            "username": "parks.canada",
            "profile_pic_url": "https://instagram.fyvr3-1.fna.fbcdn.net/t51.2885-19/s150x150/15538440_589970811191426_444632099861823488_n.jpg",
            "id": "4143631778"
        },
        "id": "17865586210091017"
    },
    {
        "text": "@saara.balagen caption \ud83d\ude00",
        "created_at": 1493494670,
        "owner": {
            "username": "jelinphilip",
            "profile_pic_url": "https://instagram.fyvr3-1.fna.fbcdn.net/t51.2885-19/s150x150/21294759_1919282618331315_7814974633257467904_a.jpg",
            "id": "249907866"
        },
        "id": "17854660366175238"
    },
    {
        "text": "Amazing shot! #explorecb",
        "created_at": 1493383496,
        "owner": {
            "username": "visitcapebretonisland",
            "profile_pic_url": "https://instagram.fyvr3-1.fna.fbcdn.net/t51.2885-19/18879403_311775499259418_5466451662145060864_a.jpg",
            "id": "1016846417"
        },
        "id": "17879122516021194"
    },
    {
        "text": "@jazzhoover",
        "created_at": 1493331948,
        "owner": {
            "username": "msglightfoot",
            "profile_pic_url": "https://instagram.fyvr3-1.fna.fbcdn.net/t51.2885-19/s150x150/17438296_1739301919700572_893190525681664000_a.jpg",
            "id": "314322784"
        },
        "id": "17879508130010229"
    },
    {
        "text": "Going there this summer!!!",
        "created_at": 1493323154,
        "owner": {
            "username": "ratkieee",
            "profile_pic_url": "https://instagram.fyvr3-1.fna.fbcdn.net/t51.2885-19/s150x150/24331738_1546852448702408_3937689754287472640_n.jpg",
            "id": "501737977"
        },
        "id": "17878883563042153"
    },
    {
        "text": "Where is is located on the trail ? Looking for a beautiful spot for a beach wedding \u2764 We already chose the Highlands but not a specific area.",
        "created_at": 1493301646,
        "owner": {
            "username": "ericamaemiehm",
            "profile_pic_url": "https://instagram.fyvr3-1.fna.fbcdn.net/t51.2885-19/s150x150/19228082_1553918717954348_3493116542722244608_a.jpg",
            "id": "14127471"
        },
        "id": "17867683093099399"
    },
    {
        "text": "Cape Breton is indeed a most beautiful place. I hope to return someday.",
        "created_at": 1493297597,
        "owner": {
            "username": "jredbreast",
            "profile_pic_url": "https://instagram.fyvr3-1.fna.fbcdn.net/t51.2885-19/s150x150/16122931_1183724461680594_4899686454914973696_a.jpg",
            "id": "1906510985"
        },
        "id": "17869491493097011"
    },
    {
        "text": "Couple petrifies after extended beach stay.",
        "created_at": 1493296905,
        "owner": {
            "username": "mrnoble63",
            "profile_pic_url": "https://instagram.fyvr3-1.fna.fbcdn.net/t51.2885-19/s150x150/25008010_175132566406991_2754119676588982272_n.jpg",
            "id": "3026160924"
        },
        "id": "17856167560145996"
    },
    {
        "text": "\u2764\u2764\u2764\u2764\u2764\u2764\u2764",
        "created_at": 1493253452,
        "owner": {
            "username": "bnatalie29",
            "profile_pic_url": "https://instagram.fyvr3-1.fna.fbcdn.net/t51.2885-19/s150x150/25010564_743041829220177_3348696287414321152_n.jpg",
            "id": "6314130"
        },
        "id": "17877814390036696"
    },
    {
        "text": "Awesome",
        "created_at": 1493252842,
        "owner": {
            "username": "sur_daniel",
            "profile_pic_url": "https://instagram.fyvr3-1.fna.fbcdn.net/t51.2885-19/s150x150/17587226_1422427831112593_7730168214780379136_a.jpg",
            "id": "3317769112"
        },
        "id": "17854290574187615"
    },
    {
        "text": "@chareric8 I would love to!",
        "created_at": 1493251452,
        "owner": {
            "username": "arieladam",
            "profile_pic_url": "https://instagram.fyvr3-1.fna.fbcdn.net/t51.2885-19/11939637_1603913843207531_1214816199_a.jpg",
            "id": "9419355"
        },
        "id": "17855348386153092"
    },
    {
        "text": "@Arieladam let's do a sister trip here....",
        "created_at": 1493249874,
        "owner": {
            "username": "chareric8",
            "profile_pic_url": "https://instagram.fyvr3-1.fna.fbcdn.net/t51.2885-19/s150x150/19984901_113295555975317_8219846322484674560_a.jpg",
            "id": "145621415"
        },
        "id": "17883076510005464"
    },
    {
        "text": "We have reservations for this summer to do some camping there and can not wait!",
        "created_at": 1493248893,
        "owner": {
            "username": "sylviakennedy613",
            "profile_pic_url": "https://instagram.fyvr3-1.fna.fbcdn.net/t51.2885-19/s150x150/12301289_1671402096472075_1138322610_a.jpg",
            "id": "2307902806"
        },
        "id": "17865215923088540"
    },
    {
        "text": "Thanks for the feature @parks.canada it's one of my favourite places for photos, that's for sure!",
        "created_at": 1493247172,
        "owner": {
            "username": "acorn_art_photography",
            "profile_pic_url": "https://instagram.fyvr3-1.fna.fbcdn.net/t51.2885-19/s150x150/24174767_186848461866488_4687985133188284416_n.jpg",
            "id": "1679491647"
        },
        "id": "17879245372049268"
    },
    {
        "text": "@samkapt  if we ever go back... we go here.",
        "created_at": 1493242223,
        "owner": {
            "username": "athomewithbrittany",
            "profile_pic_url": "https://instagram.fyvr3-1.fna.fbcdn.net/t51.2885-19/s150x150/22069151_128783387845779_7538580057397133312_n.jpg",
            "id": "175728873"
        },
        "id": "17878641898062390"
    },
    {
        "text": "\ud83d\udd25",
        "created_at": 1493240682,
        "owner": {
            "username": "soscotian.ca",
            "profile_pic_url": "https://instagram.fyvr3-1.fna.fbcdn.net/t51.2885-19/s150x150/12599111_909848979136328_920347383_a.jpg",
            "id": "2934678150"
        },
        "id": "17858237803142432"
    },
    {
        "text": "Can't wait to make our way up there this summer :)",
        "created_at": 1493240469,
        "owner": {
            "username": "emilylavenders",
            "profile_pic_url": "https://instagram.fyvr3-1.fna.fbcdn.net/t51.2885-19/s150x150/19533978_675050302687576_8881548891279851520_a.jpg",
            "id": "736743215"
        },
        "id": "17854715233166261"
    },
    {
        "text": "@sproglebee \u2661",
        "created_at": 1493240377,
        "owner": {
            "username": "outdoorlaura",
            "profile_pic_url": "https://instagram.fyvr3-1.fna.fbcdn.net/t51.2885-19/s150x150/14730712_1585777558395549_8984134120720302080_a.jpg",
            "id": "4037956857"
        },
        "id": "17867228788102945"
    }
]