{
    "owner_id": 4143631778,
    "date": "2017-03-23T14:15:27",
    "url": "https://instagram.fyvr3-1.fna.fbcdn.net/vp/29bf8a00ecb9e48ae6878817148709d5/5AE004EA/t51.2885-15/e35/17334257_1453075658070383_5825228765919182848_n.jpg",
    "typename": "GraphImage",
    "owner_username": "parks.canada",
    "caption_hashtags": [
        "nationalpuppyday",
        "dogsofinsta",
        "dogsofig",
        "puppiesofinstagram",
        "puppydog",
        "puppy",
        "puppies",
        "dog",
        "doggies",
        "dogsandpals",
        "instadog",
        "frenchbulldog",
        "frenchie",
        "westie",
        "huskiesofinstagram",
        "huskies",
        "gsd",
        "muttsofinstagram",
        "goldensofinstagram",
        "goldenretriever",
        "parkscanada",
        "canada",
        "explorecanada",
        "canada150",
        "showusyourpass"
    ],
    "shortcode": "BR_tBCqA5m7",
    "caption_mentions": [
        "kalaniwestie",
        "thorsshepherd",
        "schpoetic",
        "chayssefulton",
        "bardmac",
        "samfarrah_",
        "ahuskynamedmilo",
        "milisecond",
        "brownie_and_bailey"
    ],
    "mediaid": 1477097186465651131,
    "comments": 31,
    "is_video": false,
    "likes": 1807,
    "tagged_users": [],
    "caption": "Happy #NationalPuppyDay! Be sure to check with our parks for specific rules and restrictions for you and your beloved pup before you arrive! And be sure to always keep Fido on a leash at all times.\nPictures from @kalaniwestie, @thorsshepherd, @schpoetic, @chayssefulton, @bardmac, @samfarrah_, @ahuskynamedmilo, @milisecond, @brownie_and_bailey\n\n#Dogsofinsta #DogsofIG #puppiesofinstagram #puppydog #puppy #puppies #dog #doggies #dogsandpals #Instadog #frenchbulldog #frenchie #westie #huskiesofinstagram #huskies #gsd #muttsofinstagram #goldensofinstagram #goldenretriever #parkscanada #canada #explorecanada #canada150 #showusyourpass"
}