{
    "typename": "GraphImage",
    "date": "2016-12-23T08:11:44",
    "caption": "Who let this jolly old fellow aboard? Our science team paid a special visit to Santa at the North Pole in August! #santa #arcticscience #arctic #adventure #nicelist #canada #santaclaus",
    "url": "https://instagram.fyvr3-1.fna.fbcdn.net/vp/aea8ddf1989f91e590027da90113fba7/5ADAB236/t51.2885-15/e35/15538235_1686809311609161_6523654365952081920_n.jpg",
    "mediaid": 1411714503166469110,
    "is_video": false,
    "owner_username": "naturalresourcescanada",
    "shortcode": "BOXatxtgSP2",
    "tagged_users": [],
    "comments": 0,
    "caption_hashtags": [
        "santa",
        "arcticscience",
        "arctic",
        "adventure",
        "nicelist",
        "canada",
        "santaclaus"
    ],
    "owner_id": 4211313612,
    "likes": 18,
    "caption_mentions": []
}