{
    "typename": "GraphImage",
    "date": "2017-02-11T06:18:26",
    "caption": "It\u2019s International Day of Women and Girls in Science! Join us in celebrating #InternationalWomensDay as we profile some of NRCan\u2019s own women in science!\n#WomenInScience #NRCanSci #IWD #STEMGirls #GirlsLoveScience",
    "url": "https://instagram.fyvr3-1.fna.fbcdn.net/vp/68ae203215ecec35cd2a00a0cd589807/5AF56DD7/t51.2885-15/e35/16464705_1530212170352172_7772408921783795712_n.jpg",
    "mediaid": 1447896264472849358,
    "is_video": false,
    "owner_username": "naturalresourcescanada",
    "shortcode": "BQX9fszhOvO",
    "tagged_users": [],
    "comments": 1,
    "caption_hashtags": [
        "internationalwomensday",
        "womeninscience",
        "nrcansci",
        "iwd",
        "stemgirls",
        "girlslovescience"
    ],
    "owner_id": 4211313612,
    "likes": 31,
    "caption_mentions": []
}