{
    "likes": 175,
    "mediaid": 1499641086175813849,
    "owner_id": 4141034395,
    "is_video": false,
    "date": "2017-04-23T16:46:10",
    "caption_mentions": [],
    "owner_username": "parcs.canada",
    "url": "https://instagram.fyvr3-1.fna.fbcdn.net/vp/219eb618794cab7a71145b18644ff322/5AF91274/t51.2885-15/e35/19367131_1317599221622637_3879847179149377536_n.jpg",
    "tagged_users": [],
    "comments": 3,
    "caption": "Des c\u00f4tes accident\u00e9es et des for\u00eats temp\u00e9r\u00e9es luxuriantes : d\u00e9couvrez le meilleur des deux mondes dans la r\u00e9serve de parc national Pacific Rim! Cet \u00e9t\u00e9 sera occup\u00e9, alors assurez-vous de planifier votre voyage \u00e0 l\u2019avance pour en profiter pleinement.\u00a0\ud83d\ude09 \n#faune #nature #photographie #animaux #sauvage #animal #voyage #jouerdehors #aventure #paysage #parcscanada #canada150 #canada #conservation #explorecanada #rpnpacificrim #pacificrim #ocean #eau #tofino #plage #surf #hellobc #explorebc #colombiebritannique",
    "shortcode": "BTPy59YFyDZ",
    "typename": "GraphImage",
    "caption_hashtags": [
        "faune",
        "nature",
        "photographie",
        "animaux",
        "sauvage",
        "animal",
        "voyage",
        "jouerdehors",
        "aventure",
        "paysage",
        "parcscanada",
        "canada150",
        "canada",
        "conservation",
        "explorecanada",
        "rpnpacificrim",
        "pacificrim",
        "ocean",
        "eau",
        "tofino",
        "plage",
        "surf",
        "hellobc",
        "explorebc",
        "colombiebritannique"
    ]
}